opaque/__init__.py
opaque/build_tools/__init__.py
opaque/build_tools/builder.py
opaque/build_tools/cli.py
opaque/build_tools/nuitka_builder.py
opaque/build_tools/pyinstaller_builder.py
opaque/build_tools/templates/pyinstaller_config.py
opaque/build_tools/templates/basic_app_template/main.py
opaque/models/abstract_model.py
opaque/models/annotations.py
opaque/models/app_model.py
opaque/models/configuration.py
opaque/models/console_model.py
opaque/models/logger_model.py
opaque/models/model.py
opaque/models/notification_model.py
opaque/models/notification_settings_model.py
opaque/presenters/app_presenter.py
opaque/presenters/console_presenter.py
opaque/presenters/notification_presenter.py
opaque/presenters/presenter.py
opaque/services/console_service.py
opaque/services/logger_service.py
opaque/services/notification_service.py
opaque/services/service.py
opaque/services/settings_service.py
opaque/services/single_instance_service.py
opaque/services/theme_service.py
opaque/services/version_service.py
opaque/services/workspace_service.py
opaque/view/__init__.py
opaque/view/app_view.py
opaque/view/application.py
opaque/view/view.py
opaque/view/dialogs/__init__.py
opaque/view/dialogs/settings.py
opaque/view/dialogs/version_info.py
opaque/view/layouts/__init__.py
opaque/view/layouts/flow.py
opaque/view/widgets/__init__.py
opaque/view/widgets/closeable_tab_widget.py
opaque/view/widgets/color_picker.py
opaque/view/widgets/console_widget.py
opaque/view/widgets/mdi_window.py
opaque/view/widgets/notification_widget.py
opaque/view/widgets/toolbar.py
opaque_framework-1.0.2.dist-info/licenses/LICENSE
opaque_framework-1.0.2.dist-info/METADATA
opaque_framework-1.0.2.dist-info/WHEEL
opaque_framework-1.0.2.dist-info/entry_points.txt
opaque_framework-1.0.2.dist-info/top_level.txt
opaque_framework-1.0.2.dist-info/RECORD
