Metadata-Version: 2.4
Name: opaque-framework
Version: 1.0.2
Summary: OPAQUE - Opinionated Python Application with Qt UI for Engineering. A flexible MDI application framework for PySide6.
Author-email: Sandro Fadiga <sfadiga@gmail.com>
License: MIT
Project-URL: Homepage, https://github.com/yourusername/opaque-framework
Project-URL: Bug Tracker, https://github.com/yourusername/opaque-framework/issues
Project-URL: Documentation, https://github.com/yourusername/opaque-framework#readme
Project-URL: Source Code, https://github.com/yourusername/opaque-framework
Keywords: gui,qt,pyside6,mdi,framework,desktop,application
Classifier: Development Status :: 4 - Beta
Classifier: Intended Audience :: Developers
Classifier: License :: OSI Approved :: MIT License
Classifier: Operating System :: OS Independent
Classifier: Programming Language :: Python :: 3
Classifier: Programming Language :: Python :: 3.8
Classifier: Programming Language :: Python :: 3.9
Classifier: Programming Language :: Python :: 3.10
Classifier: Programming Language :: Python :: 3.11
Classifier: Programming Language :: Python :: 3.12
Classifier: Topic :: Software Development :: Libraries :: Application Frameworks
Classifier: Topic :: Software Development :: Libraries :: Python Modules
Classifier: Topic :: Software Development :: User Interfaces
Requires-Python: >=3.8
License-File: LICENSE
Requires-Dist: PySide6>=6.0.0
Requires-Dist: qt-material>=2.14
Requires-Dist: QDarkStyle>=3.2.0
Provides-Extra: themes
Requires-Dist: qt-themes>=1.0.0; extra == "themes"
Provides-Extra: build
Requires-Dist: pyinstaller>=5.0; extra == "build"
Requires-Dist: nuitka>=1.0; extra == "build"
Provides-Extra: dev
Requires-Dist: pytest>=7.0; extra == "dev"
Requires-Dist: pytest-qt>=4.0; extra == "dev"
Requires-Dist: black>=22.0; extra == "dev"
Requires-Dist: pylint>=2.0; extra == "dev"
Requires-Dist: mypy>=1.0; extra == "dev"
Requires-Dist: build; extra == "dev"
Requires-Dist: wheel; extra == "dev"
Dynamic: license-file
